KalaTorch/__init__.py
KalaTorch/kala_torch.py
kala_torch-1.1.8.dist-info/METADATA
kala_torch-1.1.8.dist-info/WHEEL
kala_torch-1.1.8.dist-info/top_level.txt
kala_torch-1.1.8.dist-info/RECORD
