Metadata-Version: 2.1
Name: kala_torch
Version: 1.1.8
Summary: A PyTorch-based module for easy implementation of various AI models.
Home-page: https://github.com/yourusername/kala_torch
Author: N V R K Sai Kamesh Sharma
Author-email: your-email@example.com
Classifier: Programming Language :: Python :: 3
Classifier: License :: OSI Approved :: MIT License
Classifier: Operating System :: OS Independent
Requires-Python: >=3.6
Requires-Dist: torch>=1.0
Requires-Dist: torchvision>=0.3.0
